<?xml version="1.0" encoding="utf-8" ?>
<dwsync>
<file name="json_spirit_reader.cpp" server="185.14.184.239" local="130391169600000000" remote="130391169600000000" Dst="1" />
<file name="json_spirit_error_position.h" server="185.14.184.239" local="130391169600000000" remote="130391169600000000" Dst="1" />
<file name="json_spirit_writer.cpp" server="185.14.184.239" local="130391169600000000" remote="130391169600000000" Dst="1" />
<file name="json_spirit.h" server="185.14.184.239" local="130391169600000000" remote="130391169600000000" Dst="1" />
<file name="LICENSE.txt" server="185.14.184.239" local="130391169600000000" remote="130391169600000000" Dst="1" />
<file name="json_spirit_value.cpp" server="185.14.184.239" local="130391169600000000" remote="130391169600000000" Dst="1" />
<file name="json_spirit_utils.h" server="185.14.184.239" local="130391169600000000" remote="130391169600000000" Dst="1" />
<file name="json_spirit_value.h" server="185.14.184.239" local="130391169600000000" remote="130391169600000000" Dst="1" />
<file name="json_spirit_reader_template.h" server="185.14.184.239" local="130391169600000000" remote="130391169600000000" Dst="1" />
<file name="json_spirit_writer_template.h" server="185.14.184.239" local="130391169600000000" remote="130391169600000000" Dst="1" />
<file name="json_spirit_stream_reader.h" server="185.14.184.239" local="130391169600000000" remote="130391169600000000" Dst="1" />
<file name="json_spirit_reader.h" server="185.14.184.239" local="130391169600000000" remote="130391169600000000" Dst="1" />
<file name="json_spirit_writer.h" server="185.14.184.239" local="130391169600000000" remote="130391169600000000" Dst="1" />
</dwsync>